{
    "compid": "evuqdwzl",
    "libid": "antdesign",
    "cn": "Radio",
    "ct": 1,
    "frag": {
        "dt": "AntDesign.RadioGroup\u00601[System.String], AntDesign",
        "valt": "System.String",
        "attrs": [
            {
                "attrn": "TValue",
                "attrt": "System.String"
            }
        ]
    },
    "ds": {
        "dsfrag": {
            "t": "AntDesign.Radio\u00601[System.String], AntDesign",
            "attrs": [
                {
                    "attrn": "Value"
                }
            ]
        },
        "dsgt": 1
    },
    "attrdefgroups": [],
    "childs": [],
    "order": 13,
    "pub": 1,
    "mt": "2025-03-23T07:26:31.4273273Z",
    "id": "lkmww2hq",
    "lb": "单选框-A",
    "sptds": true,
    "stl": {
        "itemh": 85,
        "labelw": 180,
        "display": "inline",
        "pos": "static"
    },
    "ev": {}
}